airQInsight/__init__.py
airQInsight/app.py
airQInsight/model.py
airQInsight/util.py
airQInsight-0.2.5.dist-info/entry_points.txt
airQInsight-0.2.5.dist-info/LICENSE
airQInsight-0.2.5.dist-info/WHEEL
airQInsight-0.2.5.dist-info/METADATA
airQInsight-0.2.5.dist-info/RECORD
