Metadata-Version: 2.1
Name: airQInsight
Version: 0.2.5
Summary: A tool designed to power exploratory data analysis, on airQ collected Air Quality Indicator Data.
Home-page: https://github.com/itzmeanjan/airQ-insight/
License: UNKNOWN
Author: Anjan Roy
Author-email: anjanroy@yandex.com
Requires-Python: >=3.7
Classifier: License :: OSI Approved :: MIT License
Requires-Dist: matplotlib
Requires-Dist: typing
Requires-Dist: airQ
Requires-Dist: flit ; extra == "dev"
Provides-Extra: dev
